stopwds/__init__.py
stopwds/__version__.py
stopwds/cli.py
stopwds/paths.py
stopwds/datasets/stopwords/cn/baidu_stopwords.txt
stopwds/datasets/stopwords/cn/cn_stopwords.txt
stopwds/datasets/stopwords/cn/hit_stopwords.txt
stopwds/datasets/stopwords/cn/scu_stopwords.txt
stopwds-0.1.5.data/data/LICENSE
stopwds-0.1.5.dist-info/LICENSE
stopwds-0.1.5.dist-info/METADATA
stopwds-0.1.5.dist-info/WHEEL
stopwds-0.1.5.dist-info/entry_points.txt
stopwds-0.1.5.dist-info/top_level.txt
stopwds-0.1.5.dist-info/RECORD
