Metadata-Version: 2.1
Name: stopwds
Version: 0.1.5
Summary: Stopwords in NLP 🦜
Home-page: https://github.com/szj2ys/stopwds
Author: szj
Author-email: szj2ys@qq.com
License: MIT
Platform: UNKNOWN
Classifier: License :: OSI Approved :: MIT License
Classifier: Programming Language :: Python :: 3.6
Classifier: Programming Language :: Python :: 3.7
Classifier: Programming Language :: Python :: 3.8
Classifier: Programming Language :: Python :: 3.9
Requires-Python: >=3.6.0
Requires-Dist: click
Requires-Dist: click-help-colors
Requires-Dist: numpy
